filepart/__init__.py
filepart/__main__.py
filepart/build.py
filepart/split.py
filepart/utils.py
filepart/wizard.py
filepart-0.1.0.data/scripts/filepart
filepart-0.1.0.dist-info/LICENSE
filepart-0.1.0.dist-info/METADATA
filepart-0.1.0.dist-info/WHEEL
filepart-0.1.0.dist-info/top_level.txt
filepart-0.1.0.dist-info/RECORD
