Metadata-Version: 2.1
Name: filepart
Version: 0.1.0
Summary: Split files into separate parts
Home-page: https://github.com/UnknownPlayer78/filepart
Author: UnknownPlayer78
Author-email: info@tearlabs.xyz
License: UNKNOWN
Platform: UNKNOWN
Classifier: Programming Language :: Python :: 3
Classifier: License :: OSI Approved :: MIT License
Classifier: Operating System :: OS Independent
Requires-Python: >=3.2
